[
  {
    "ContainingType": "WebApiPropiedades.Controllers.AccountController",
    "Method": "ForgotPassword",
    "RelativePath": "api/Account/forgot-password",
    "HttpMethod": "POST",
    "IsController": true,
    "Order": 0,
    "Parameters": [
      {
        "Name": "forgotPasswordDto",
        "Type": "WebApiPropiedades.Dtos.Account.ForgotPasswordDto",
        "IsRequired": true
      }
    ],
    "ReturnTypes": []
  },
  {
    "ContainingType": "WebApiPropiedades.Controllers.AccountController",
    "Method": "Login",
    "RelativePath": "api/Account/login",
    "HttpMethod": "POST",
    "IsController": true,
    "Order": 0,
    "Parameters": [
      {
        "Name": "loginReqDto",
        "Type": "WebApiPropiedades.Dtos.Account.LoginReqDto",
        "IsRequired": true
      }
    ],
    "ReturnTypes": []
  },
  {
    "ContainingType": "WebApiPropiedades.Controllers.AccountController",
    "Method": "Register",
    "RelativePath": "api/Account/register",
    "HttpMethod": "POST",
    "IsController": true,
    "Order": 0,
    "Parameters": [
      {
        "Name": "registerReqDto",
        "Type": "WebApiPropiedades.Dtos.Account.RegisterReqDto",
        "IsRequired": true
      }
    ],
    "ReturnTypes": []
  },
  {
    "ContainingType": "WebApiPropiedades.Controllers.AccountController",
    "Method": "ResetPassword",
    "RelativePath": "api/Account/reset-password",
    "HttpMethod": "POST",
    "IsController": true,
    "Order": 0,
    "Parameters": [
      {
        "Name": "resetPasswordDto",
        "Type": "WebApiPropiedades.Dtos.Account.ResetPasswordDto",
        "IsRequired": true
      }
    ],
    "ReturnTypes": []
  },
  {
    "ContainingType": "WebApiPropiedades.Controllers.CityController",
    "Method": "GetCity",
    "RelativePath": "api/City/{id}",
    "HttpMethod": "GET",
    "IsController": true,
    "Order": 0,
    "Parameters": [
      {
        "Name": "id",
        "Type": "System.Int32",
        "IsRequired": true
      }
    ],
    "ReturnTypes": []
  },
  {
    "ContainingType": "WebApiPropiedades.Controllers.CityController",
    "Method": "GetCities",
    "RelativePath": "api/City/cities",
    "HttpMethod": "GET",
    "IsController": true,
    "Order": 0,
    "Parameters": [],
    "ReturnTypes": []
  },
  {
    "ContainingType": "WebApiPropiedades.Controllers.CityController",
    "Method": "DeleteCity",
    "RelativePath": "api/City/delete/{id}",
    "HttpMethod": "DELETE",
    "IsController": true,
    "Order": 0,
    "Parameters": [
      {
        "Name": "id",
        "Type": "System.Int32",
        "IsRequired": true
      }
    ],
    "ReturnTypes": []
  },
  {
    "ContainingType": "WebApiPropiedades.Controllers.CityController",
    "Method": "AddCity",
    "RelativePath": "api/City/post",
    "HttpMethod": "POST",
    "IsController": true,
    "Order": 0,
    "Parameters": [
      {
        "Name": "cityDto",
        "Type": "WebApiPropiedades.Dtos.City.CityCreateDto",
        "IsRequired": true
      }
    ],
    "ReturnTypes": []
  },
  {
    "ContainingType": "WebApiPropiedades.Controllers.CityController",
    "Method": "UpdateCity",
    "RelativePath": "api/City/update/{id}",
    "HttpMethod": "PUT",
    "IsController": true,
    "Order": 0,
    "Parameters": [
      {
        "Name": "id",
        "Type": "System.Int32",
        "IsRequired": true
      },
      {
        "Name": "cityDto",
        "Type": "WebApiPropiedades.Dtos.City.CityUpdateDto",
        "IsRequired": true
      }
    ],
    "ReturnTypes": []
  },
  {
    "ContainingType": "WebApiPropiedades.Controllers.CityController",
    "Method": "UpdateCityPatch",
    "RelativePath": "api/City/update/{id}",
    "HttpMethod": "PATCH",
    "IsController": true,
    "Order": 0,
    "Parameters": [
      {
        "Name": "id",
        "Type": "System.Int32",
        "IsRequired": true
      },
      {
        "Name": "cityToPatch",
        "Type": "Microsoft.AspNetCore.JsonPatch.Operations.Operation[]",
        "IsRequired": true
      }
    ],
    "ReturnTypes": []
  },
  {
    "ContainingType": "WebApiPropiedades.Controllers.CityController",
    "Method": "UpdateCityName",
    "RelativePath": "api/City/updateCityName/{id}",
    "HttpMethod": "PUT",
    "IsController": true,
    "Order": 0,
    "Parameters": [
      {
        "Name": "id",
        "Type": "System.Int32",
        "IsRequired": true
      },
      {
        "Name": "cityDto",
        "Type": "WebApiPropiedades.Dtos.City.CityUpdateDto",
        "IsRequired": true
      }
    ],
    "ReturnTypes": []
  },
  {
    "ContainingType": "WebApiPropiedades.Controllers.FurnishingTypeController",
    "Method": "AddFurnishingType",
    "RelativePath": "api/FurnishingType",
    "HttpMethod": "POST",
    "IsController": true,
    "Order": 0,
    "Parameters": [
      {
        "Name": "furnishingTypeDto",
        "Type": "WebApiPropiedades.Dtos.FurnishingType.FurnishingTypeCreateDto",
        "IsRequired": true
      }
    ],
    "ReturnTypes": []
  },
  {
    "ContainingType": "WebApiPropiedades.Controllers.FurnishingTypeController",
    "Method": "GetFurnishingType",
    "RelativePath": "api/FurnishingType/{id}",
    "HttpMethod": "GET",
    "IsController": true,
    "Order": 0,
    "Parameters": [
      {
        "Name": "id",
        "Type": "System.Int32",
        "IsRequired": true
      }
    ],
    "ReturnTypes": []
  },
  {
    "ContainingType": "WebApiPropiedades.Controllers.FurnishingTypeController",
    "Method": "UpdateFurnishingType",
    "RelativePath": "api/FurnishingType/{id}",
    "HttpMethod": "PUT",
    "IsController": true,
    "Order": 0,
    "Parameters": [
      {
        "Name": "id",
        "Type": "System.Int32",
        "IsRequired": true
      },
      {
        "Name": "furnishingTypeDto",
        "Type": "WebApiPropiedades.Dtos.FurnishingType.FurnishingTypeUpdateDto",
        "IsRequired": true
      }
    ],
    "ReturnTypes": []
  },
  {
    "ContainingType": "WebApiPropiedades.Controllers.FurnishingTypeController",
    "Method": "DeleteFurnishingType",
    "RelativePath": "api/FurnishingType/{id}",
    "HttpMethod": "DELETE",
    "IsController": true,
    "Order": 0,
    "Parameters": [
      {
        "Name": "id",
        "Type": "System.Int32",
        "IsRequired": true
      }
    ],
    "ReturnTypes": []
  },
  {
    "ContainingType": "WebApiPropiedades.Controllers.FurnishingTypeController",
    "Method": "GetFurnishingTypes",
    "RelativePath": "api/FurnishingType/list",
    "HttpMethod": "GET",
    "IsController": true,
    "Order": 0,
    "Parameters": [],
    "ReturnTypes": []
  },
  {
    "ContainingType": "WebApiPropiedades.Controllers.FurnishingTypeController",
    "Method": "UpdateFurnishingTypePatch",
    "RelativePath": "api/FurnishingType/update/{id}",
    "HttpMethod": "PATCH",
    "IsController": true,
    "Order": 0,
    "Parameters": [
      {
        "Name": "id",
        "Type": "System.Int32",
        "IsRequired": true
      },
      {
        "Name": "furnishingTypeToPatch",
        "Type": "Microsoft.AspNetCore.JsonPatch.Operations.Operation[]",
        "IsRequired": true
      }
    ],
    "ReturnTypes": []
  },
  {
    "ContainingType": "WebApiPropiedades.Controllers.PropertyController",
    "Method": "DeleteProperty",
    "RelativePath": "api/Property/{id}",
    "HttpMethod": "DELETE",
    "IsController": true,
    "Order": 0,
    "Parameters": [
      {
        "Name": "id",
        "Type": "System.Int32",
        "IsRequired": true
      }
    ],
    "ReturnTypes": []
  },
  {
    "ContainingType": "WebApiPropiedades.Controllers.PropertyController",
    "Method": "AddProperty",
    "RelativePath": "api/Property/add",
    "HttpMethod": "POST",
    "IsController": true,
    "Order": 0,
    "Parameters": [
      {
        "Name": "propertyDto",
        "Type": "WebApiPropiedades.Dtos.Property.PropertyDto",
        "IsRequired": true
      }
    ],
    "ReturnTypes": []
  },
  {
    "ContainingType": "WebApiPropiedades.Controllers.PropertyController",
    "Method": "UploadPropertyImage",
    "RelativePath": "api/Property/add/photo/{id}",
    "HttpMethod": "POST",
    "IsController": true,
    "Order": 0,
    "Parameters": [
      {
        "Name": "id",
        "Type": "System.Int32",
        "IsRequired": true
      },
      {
        "Name": "file",
        "Type": "Microsoft.AspNetCore.Http.IFormFile",
        "IsRequired": false
      }
    ],
    "ReturnTypes": []
  },
  {
    "ContainingType": "WebApiPropiedades.Controllers.PropertyController",
    "Method": "GetPropertyDetail",
    "RelativePath": "api/Property/detail/{id}",
    "HttpMethod": "GET",
    "IsController": true,
    "Order": 0,
    "Parameters": [
      {
        "Name": "id",
        "Type": "System.Int32",
        "IsRequired": true
      }
    ],
    "ReturnTypes": []
  },
  {
    "ContainingType": "WebApiPropiedades.Controllers.PropertyController",
    "Method": "GetProperties",
    "RelativePath": "api/Property/list/{sellRent}",
    "HttpMethod": "GET",
    "IsController": true,
    "Order": 0,
    "Parameters": [
      {
        "Name": "sellRent",
        "Type": "System.Int32",
        "IsRequired": true
      }
    ],
    "ReturnTypes": []
  },
  {
    "ContainingType": "WebApiPropiedades.Controllers.PropertyController",
    "Method": "UpdateProperty",
    "RelativePath": "api/Property/update/{id}",
    "HttpMethod": "PUT",
    "IsController": true,
    "Order": 0,
    "Parameters": [
      {
        "Name": "id",
        "Type": "System.Int32",
        "IsRequired": true
      },
      {
        "Name": "propertyDto",
        "Type": "WebApiPropiedades.Dtos.Property.PropertyUpdateDto",
        "IsRequired": true
      }
    ],
    "ReturnTypes": []
  },
  {
    "ContainingType": "WebApiPropiedades.Controllers.PropertyTypeController",
    "Method": "AddPropertyType",
    "RelativePath": "api/PropertyType",
    "HttpMethod": "POST",
    "IsController": true,
    "Order": 0,
    "Parameters": [
      {
        "Name": "propertyTypeDto",
        "Type": "WebApiPropiedades.Dtos.PropertyType.PropertyTypeCreateDto",
        "IsRequired": true
      }
    ],
    "ReturnTypes": []
  },
  {
    "ContainingType": "WebApiPropiedades.Controllers.PropertyTypeController",
    "Method": "UpdatePropertyType",
    "RelativePath": "api/PropertyType",
    "HttpMethod": "PUT",
    "IsController": true,
    "Order": 0,
    "Parameters": [
      {
        "Name": "id",
        "Type": "System.Int32",
        "IsRequired": false
      },
      {
        "Name": "propertyTypeDto",
        "Type": "WebApiPropiedades.Dtos.PropertyType.PropertyTypeUpdateDto",
        "IsRequired": true
      }
    ],
    "ReturnTypes": []
  },
  {
    "ContainingType": "WebApiPropiedades.Controllers.PropertyTypeController",
    "Method": "DeletePropertyType",
    "RelativePath": "api/PropertyType/{id}",
    "HttpMethod": "DELETE",
    "IsController": true,
    "Order": 0,
    "Parameters": [
      {
        "Name": "id",
        "Type": "System.Int32",
        "IsRequired": true
      }
    ],
    "ReturnTypes": []
  },
  {
    "ContainingType": "WebApiPropiedades.Controllers.PropertyTypeController",
    "Method": "GetPropertyTypes",
    "RelativePath": "api/PropertyType/list",
    "HttpMethod": "GET",
    "IsController": true,
    "Order": 0,
    "Parameters": [],
    "ReturnTypes": []
  },
  {
    "ContainingType": "WebApiPropiedades.Controllers.PropertyTypeController",
    "Method": "GetPropertyType",
    "RelativePath": "api/PropertyType/propertyType/{id}",
    "HttpMethod": "GET",
    "IsController": true,
    "Order": 0,
    "Parameters": [
      {
        "Name": "id",
        "Type": "System.Int32",
        "IsRequired": true
      }
    ],
    "ReturnTypes": []
  }
]